{"cameraMode":{"drawMode":0,"name":"Shaded","section":"Shading Mode"},"sceneLighting":true,"audioPlay":false,"sceneViewState":{"showFog":true,"showMaterialUpdate":false,"showSkybox":true,"showFlares":true,"showImageEffects":true,"showParticleSystems":true,"showVisualEffectGraphs":true,"m_FxEnabled":true},"in2DMode":false,"pivot":{"x":8.411125183105469,"y":0.6039142608642578,"z":22.940200805664064},"rotation":{"x":0.1421552449464798,"y":0.6678271889686585,"z":-0.13211943209171296,"w":0.7185761332511902},"size":18.098283767700197,"orthographic":false}